MANIFEST.in
README.rst
setup.py
chore/__init__.py
chore/admin.py
chore/apps.py
chore/cache_mixin.py
chore/chore_api.py
chore/connector.py
chore/models.py
chore/oauth_api.py
chore/tests.py
chore/urls.py
chore/views.py
chore/migrations/__init__.py
chore/restful/__init__.py
chore/restful/fields.py
chore/restful/filters.py
chore/restful/pagination.py
chore/restful/permissions.py
chore/restful/renderers.py
chore/restful/serializers.py
chore/restful/viewsets.py
integra_chore.egg-info/PKG-INFO
integra_chore.egg-info/SOURCES.txt
integra_chore.egg-info/dependency_links.txt
integra_chore.egg-info/requires.txt
integra_chore.egg-info/top_level.txt
integra_chore.egg-info/zip-safe