Metadata-Version: 1.0
Name: integra-chore
Version: 1.0.5
Summary: A django chore app with angularjs and bootstrap
Home-page: UNKNOWN
Author: Partha.Konda
Author-email: parthasaradhi1992@gmail.com
License: UNKNOWN
Keywords: django-authentication,integra-authentication
Platform: UNKNOWN
